{
  "kind": "collectionType",
  "collectionName": "articles",
  "info": {
    "singularName": "article",
    "pluralName": "articles",
    "displayName": "Article"
  },
  "options": {
    "draftAndPublish": true
  },
  "pluginOptions": {},
  "attributes": {
    "Title": {
      "type": "string",
      "required": true
    },
    "Client_Scope": {
      "type": "enumeration",
      "required": true,
      "enum": [
        "GRN",
        "LTL_FRANCE"
      ]
    },
    "Content": {
      "type": "customField",
      "customField": "plugin::ckeditor5.CKEditor",
      "options": {
        "preset": "defaultHtml"
      },
      "required": true
    }
  }
}
